optgbm/__init__.py
optgbm/compat.py
optgbm/sklearn.py
optgbm/typing.py
optgbm/utils.py
OptGBM-0.10.0.dist-info/LICENSE
OptGBM-0.10.0.dist-info/METADATA
OptGBM-0.10.0.dist-info/WHEEL
OptGBM-0.10.0.dist-info/top_level.txt
OptGBM-0.10.0.dist-info/RECORD
