Metadata-Version: 2.1
Name: OptGBM
Version: 0.10.0
Summary: Optuna + LightGBM \= OptGBM
Home-page: UNKNOWN
Author: Kon
License: MIT License
Platform: UNKNOWN
Requires-Python: >=3.6
Requires-Dist: lightgbm (>=2.2.2)
Requires-Dist: numpy
Requires-Dist: optuna (>=0.17)
Requires-Dist: pandas
Requires-Dist: scikit-learn (>=0.19.0)
Provides-Extra: testing
Requires-Dist: matplotlib ; extra == 'testing'
